{"metadata":{},"options":{"compact":false,"sourceMaps":true,"ast":true,"babelrc":false,"configFile":false,"parserOpts":{"sourceType":"module","sourceFileName":"/Users/gunwoo/OneDrive/College/2020Fall/CSE330S/creativeproject-module7-457175-476801/hotel/imports/ui/App.vue","plugins":["*","flow","jsx","asyncGenerators","bigInt","classPrivateMethods","classPrivateProperties","classProperties","doExpressions","dynamicImport","exportDefaultFrom","exportExtensions","exportNamespaceFrom","functionBind","functionSent","importMeta","nullishCoalescingOperator","numericSeparator","objectRestSpread","optionalCatchBinding","optionalChaining",["pipelineOperator",{"proposal":"minimal"}],"throwExpressions",["flow",{}],"nullishCoalescingOperator","nullishCoalescingOperator","optionalChaining","optionalChaining","optionalCatchBinding","optionalCatchBinding","classProperties","classPrivateProperties","classPrivateMethods","classProperties","classPrivateProperties","asyncGenerators","asyncGenerators","objectRestSpread","objectRestSpread",["flow",{}]],"allowImportExportEverywhere":true,"allowReturnOutsideFunction":true,"allowUndeclaredExports":true,"strictMode":false},"sourceFileName":"/Users/gunwoo/OneDrive/College/2020Fall/CSE330S/creativeproject-module7-457175-476801/hotel/imports/ui/App.vue","filename":"/Users/gunwoo/OneDrive/College/2020Fall/CSE330S/creativeproject-module7-457175-476801/hotel/imports/ui/App.vue","passPerPreset":false,"envName":"development","cwd":"/Users/gunwoo/OneDrive/College/2020Fall/CSE330S/creativeproject-module7-457175-476801/hotel","root":"/Users/gunwoo/OneDrive/College/2020Fall/CSE330S/creativeproject-module7-457175-476801/hotel","plugins":[{"key":"base$0","visitor":{"_exploded":true,"_verified":true},"options":{}},{"key":"base$0$0","visitor":{"Program":{"enter":[null],"exit":[null]},"_exploded":true,"_verified":true},"options":{"avoidModernSyntax":true,"enforceStrictMode":false,"dynamicImport":true}},{"key":"transform-runtime","visitor":{"CallExpression":{"enter":[null]},"BinaryExpression":{"enter":[null]},"MemberExpression":{"enter":[null],"exit":[null]},"_exploded":true,"_verified":true,"Identifier":{"enter":[null]},"JSXIdentifier":{"enter":[null]}},"options":{"version":"7.7.6","helpers":true,"useESModules":false,"corejs":false}},{"key":"syntax-flow","visitor":{"_exploded":true,"_verified":true},"options":{}},{"key":"syntax-nullish-coalescing-operator","visitor":{"_exploded":true,"_verified":true},"options":{}},{"key":"proposal-nullish-coalescing-operator","visitor":{"_exploded":{},"_verified":{},"LogicalExpression":{"enter":[null]}},"options":{}},{"key":"syntax-optional-chaining","visitor":{"_exploded":true,"_verified":true},"options":{}},{"key":"proposal-optional-chaining","visitor":{"_exploded":{},"_verified":{},"OptionalCallExpression":{"enter":[null]},"OptionalMemberExpression":{"enter":[null]}},"options":{}},{"key":"syntax-optional-catch-binding","visitor":{"_exploded":true,"_verified":true},"options":{}},{"key":"proposal-optional-catch-binding","visitor":{"_exploded":{},"_verified":{},"CatchClause":{"enter":[null]}},"options":{}},{"key":"syntax-class-properties","visitor":{"_exploded":true,"_verified":true},"options":{}},{"key":"proposal-class-properties","visitor":{"PrivateName":{"enter":[null]},"ExportDefaultDeclaration":{"enter":[null]},"_exploded":true,"_verified":true,"ClassDeclaration":{"enter":[null]},"ClassExpression":{"enter":[null]}},"options":{}},{"key":"syntax-async-generators","visitor":{"_exploded":true,"_verified":true},"options":{}},{"key":"proposal-async-generator-functions","visitor":{"_exploded":{},"_verified":{},"Program":{"enter":[null]}},"options":{}},{"key":"syntax-object-rest-spread","visitor":{"_exploded":true,"_verified":true},"options":{}},{"key":"proposal-object-rest-spread","visitor":{"_exploded":{},"_verified":{},"VariableDeclarator":{"enter":[null]},"ExportNamedDeclaration":{"enter":[null]},"CatchClause":{"enter":[null]},"AssignmentExpression":{"enter":[null]},"ArrayPattern":{"enter":[null]},"ObjectExpression":{"enter":[null]},"FunctionDeclaration":{"enter":[null]},"FunctionExpression":{"enter":[null]},"ObjectMethod":{"enter":[null]},"ArrowFunctionExpression":{"enter":[null]},"ClassMethod":{"enter":[null]},"ClassPrivateMethod":{"enter":[null]},"ForInStatement":{"enter":[null]},"ForOfStatement":{"enter":[null]}},"options":{}},{"key":"transform-arrow-functions","visitor":{"ArrowFunctionExpression":{"enter":[null]},"_exploded":true,"_verified":true},"options":{}},{"key":"transform-block-scoped-functions","visitor":{"BlockStatement":{"enter":[null]},"SwitchCase":{"enter":[null]},"_exploded":true,"_verified":true},"options":{}},{"key":"transform-block-scoping","visitor":{"VariableDeclaration":{"enter":[null]},"CatchClause":{"enter":[null]},"_exploded":true,"BlockStatement":{"enter":[null]},"SwitchStatement":{"enter":[null]},"Program":{"enter":[null]},"_verified":true,"DoWhileStatement":{"enter":[null]},"ForInStatement":{"enter":[null]},"ForStatement":{"enter":[null]},"WhileStatement":{"enter":[null]},"ForOfStatement":{"enter":[null]}},"options":{}},{"key":"transform-classes","visitor":{"ExportDefaultDeclaration":{"enter":[null]},"ClassDeclaration":{"enter":[null]},"ClassExpression":{"enter":[null]},"_exploded":true,"_verified":true},"options":{"loose":true}},{"key":"transform-computed-properties","visitor":{"ObjectExpression":{"exit":[null]},"_exploded":true,"_verified":true},"options":{"loose":true}},{"key":"transform-destructuring","visitor":{"ExportNamedDeclaration":{"enter":[null]},"CatchClause":{"enter":[null]},"AssignmentExpression":{"enter":[null]},"VariableDeclaration":{"enter":[null]},"_exploded":true,"_verified":true,"ForInStatement":{"enter":[null]},"ForOfStatement":{"enter":[null]}},"options":{}},{"key":"transform-for-of","visitor":{"ForOfStatement":{"enter":[null]},"_exploded":true,"_verified":true},"options":{"loose":true}},{"key":"transform-literals","visitor":{"NumericLiteral":{"enter":[null]},"StringLiteral":{"enter":[null]},"_exploded":true,"_verified":true},"options":{}},{"key":"transform-object-super","visitor":{"ObjectExpression":{"enter":[null]},"_exploded":true,"_verified":true},"options":{}},{"key":"transform-parameters","visitor":{"_exploded":true,"_verified":true,"FunctionDeclaration":{"enter":[null]},"FunctionExpression":{"enter":[null]},"ObjectMethod":{"enter":[null]},"ArrowFunctionExpression":{"enter":[null]},"ClassMethod":{"enter":[null]},"ClassPrivateMethod":{"enter":[null]}},"options":{}},{"key":"transform-shorthand-properties","visitor":{"ObjectMethod":{"enter":[null]},"ObjectProperty":{"enter":[null]},"_exploded":true,"_verified":true},"options":{}},{"key":"transform-spread","visitor":{"ArrayExpression":{"enter":[null]},"CallExpression":{"enter":[null]},"NewExpression":{"enter":[null]},"_exploded":true,"_verified":true},"options":{}},{"key":"transform-sticky-regex","visitor":{"RegExpLiteral":{"enter":[null]},"_exploded":true,"_verified":true},"options":{}},{"key":"transform-template-literals","visitor":{"TaggedTemplateExpression":{"enter":[null]},"TemplateLiteral":{"enter":[null]},"_exploded":true,"_verified":true},"options":{"loose":true}},{"key":"transform-typeof-symbol","visitor":{"UnaryExpression":{"enter":[null]},"_exploded":true,"_verified":true,"BlockStatement":{"enter":[null]},"CatchClause":{"enter":[null]},"DoWhileStatement":{"enter":[null]},"ForInStatement":{"enter":[null]},"ForStatement":{"enter":[null]},"FunctionDeclaration":{"enter":[null]},"FunctionExpression":{"enter":[null]},"Program":{"enter":[null]},"ObjectMethod":{"enter":[null]},"SwitchStatement":{"enter":[null]},"WhileStatement":{"enter":[null]},"ArrowFunctionExpression":{"enter":[null]},"ClassDeclaration":{"enter":[null]},"ClassExpression":{"enter":[null]},"ForOfStatement":{"enter":[null]},"ClassMethod":{"enter":[null]},"ClassPrivateMethod":{"enter":[null]},"TSModuleBlock":{"enter":[null]}},"options":{}},{"key":"transform-unicode-regex","visitor":{"RegExpLiteral":{"enter":[null]},"_exploded":true,"_verified":true},"options":{}},{"key":"transform-property-literals","visitor":{"ObjectProperty":{"exit":[null]},"_exploded":true,"_verified":true},"options":{}},{"key":"transform-flow-strip-types","visitor":{"_exploded":{},"_verified":{},"Program":{"enter":[null]},"ImportDeclaration":{"enter":[null,null]},"ClassProperty":{"enter":[null]},"ClassPrivateProperty":{"enter":[null]},"AssignmentPattern":{"enter":[null]},"TypeCastExpression":{"enter":[null,null]},"CallExpression":{"enter":[null]},"OptionalCallExpression":{"enter":[null]},"NewExpression":{"enter":[null]},"ImportSpecifier":{"enter":[null]},"ClassDeclaration":{"enter":[null]},"ClassExpression":{"enter":[null]},"FunctionDeclaration":{"enter":[null]},"FunctionExpression":{"enter":[null]},"ObjectMethod":{"enter":[null]},"ArrowFunctionExpression":{"enter":[null]},"ClassMethod":{"enter":[null]},"ClassPrivateMethod":{"enter":[null]},"AnyTypeAnnotation":{"enter":[null]},"ArrayTypeAnnotation":{"enter":[null]},"BooleanTypeAnnotation":{"enter":[null]},"BooleanLiteralTypeAnnotation":{"enter":[null]},"NullLiteralTypeAnnotation":{"enter":[null]},"ClassImplements":{"enter":[null]},"DeclareClass":{"enter":[null]},"DeclareFunction":{"enter":[null]},"DeclareInterface":{"enter":[null]},"DeclareModule":{"enter":[null]},"DeclareModuleExports":{"enter":[null]},"DeclareTypeAlias":{"enter":[null]},"DeclareOpaqueType":{"enter":[null]},"DeclareVariable":{"enter":[null]},"DeclareExportDeclaration":{"enter":[null]},"DeclareExportAllDeclaration":{"enter":[null]},"DeclaredPredicate":{"enter":[null]},"ExistsTypeAnnotation":{"enter":[null]},"FunctionTypeAnnotation":{"enter":[null]},"FunctionTypeParam":{"enter":[null]},"GenericTypeAnnotation":{"enter":[null]},"InferredPredicate":{"enter":[null]},"InterfaceExtends":{"enter":[null]},"InterfaceDeclaration":{"enter":[null]},"InterfaceTypeAnnotation":{"enter":[null]},"IntersectionTypeAnnotation":{"enter":[null]},"MixedTypeAnnotation":{"enter":[null]},"EmptyTypeAnnotation":{"enter":[null]},"NullableTypeAnnotation":{"enter":[null]},"NumberLiteralTypeAnnotation":{"enter":[null]},"NumberTypeAnnotation":{"enter":[null]},"ObjectTypeAnnotation":{"enter":[null]},"ObjectTypeInternalSlot":{"enter":[null]},"ObjectTypeCallProperty":{"enter":[null]},"ObjectTypeIndexer":{"enter":[null]},"ObjectTypeProperty":{"enter":[null]},"ObjectTypeSpreadProperty":{"enter":[null]},"OpaqueType":{"enter":[null]},"QualifiedTypeIdentifier":{"enter":[null]},"StringLiteralTypeAnnotation":{"enter":[null]},"StringTypeAnnotation":{"enter":[null]},"ThisTypeAnnotation":{"enter":[null]},"TupleTypeAnnotation":{"enter":[null]},"TypeofTypeAnnotation":{"enter":[null]},"TypeAlias":{"enter":[null]},"TypeAnnotation":{"enter":[null]},"TypeParameter":{"enter":[null]},"TypeParameterDeclaration":{"enter":[null]},"TypeParameterInstantiation":{"enter":[null]},"UnionTypeAnnotation":{"enter":[null]},"Variance":{"enter":[null]},"VoidTypeAnnotation":{"enter":[null]},"ExportAllDeclaration":{"enter":[null]},"ExportDefaultDeclaration":{"enter":[null]},"ExportNamedDeclaration":{"enter":[null]}},"options":{}},{"key":"transform-exponentiation-operator","visitor":{"AssignmentExpression":{"enter":[null]},"BinaryExpression":{"enter":[null]},"_exploded":true,"_verified":true},"options":{}},{"key":"regenerator-transform","visitor":{"_exploded":true,"_verified":true,"ObjectMethod":{"enter":[null],"exit":[null]},"ClassMethod":{"enter":[null],"exit":[null]},"ClassPrivateMethod":{"enter":[null],"exit":[null]},"FunctionDeclaration":{"exit":[null]},"FunctionExpression":{"exit":[null]},"ArrowFunctionExpression":{"exit":[null]}},"options":{}}],"presets":[],"generatorOpts":{"filename":"/Users/gunwoo/OneDrive/College/2020Fall/CSE330S/creativeproject-module7-457175-476801/hotel/imports/ui/App.vue","comments":true,"compact":false,"sourceMaps":true,"sourceFileName":"/Users/gunwoo/OneDrive/College/2020Fall/CSE330S/creativeproject-module7-457175-476801/hotel/imports/ui/App.vue"}},"code":"var Vue;\nmodule.link(\"vue\", {\n  \"default\": function (v) {\n    Vue = v;\n  }\n}, 0);\nvar Meteor;\nmodule.link(\"meteor/meteor\", {\n  Meteor: function (v) {\n    Meteor = v;\n  }\n}, 1);\nvar Accounts;\nmodule.link(\"meteor/accounts-base\", {\n  Accounts: function (v) {\n    Accounts = v;\n  }\n}, 2);\nvar Items;\nmodule.link(\"../api/items.js\", {\n  Items: function (v) {\n    Items = v;\n  }\n}, 3);\nvar Carts;\nmodule.link(\"../api/items.js\", {\n  Carts: function (v) {\n    Carts = v;\n  }\n}, 4);\nvar Rooms;\nmodule.link(\"../api/items.js\", {\n  Rooms: function (v) {\n    Rooms = v;\n  }\n}, 5);\nmodule.exportDefault({\n  components: {},\n  data: function () {\n    return {\n      user: \"\",\n      username: null,\n      password: \"\",\n      userID: \"\",\n      profile: null,\n      loggedIn: false,\n      save_Item_Name: \"\",\n      save_Item_Description: \"\",\n      ordered_items: null,\n      save_room_data: null,\n      room_number: null\n    };\n  },\n  methods: {\n    register_client: function (event) {\n      Meteor.call(\"addUser\", this.user, this.password, \"guest\", this.room_number, function (error) {\n        alert(error.reason);\n      });\n      user = \"\", password = \"\";\n    },\n    register_manager: function (event) {\n      Meteor.call(\"addUser\", this.user, this.password, \"manager\", null, function (error) {\n        alert(error.reason);\n      });\n      user = \"\", password = \"\";\n    },\n    login: function (event) {\n      Meteor.loginWithPassword(this.user, this.password, function (error) {\n        alert(error.reason);\n      });\n    },\n    logout: function (event) {\n      Meteor.logout();\n    },\n    save_Item: function (event) {\n      Items.insert({\n        name: this.save_Item_Name,\n        description: this.save_Item_Description\n      });\n      this.save_Item_Name = \"\", this.save_Item_Description = \"\";\n    },\n    order: function (event) {\n      console.log(this.ordered_items);\n    },\n    deleteThisItem: function (item_id) {\n      Items.remove(item_id);\n    },\n    addToCart: function (id, name) {\n      Carts.insert({\n        item: id,\n        username: Meteor.user().username,\n        userID: Meteor.userId(),\n        status: \"Added To Cart\",\n        name: name,\n        createdAt: new Date()\n      });\n    },\n    deleteFromCart: function (item_id) {\n      Carts.remove(item_id);\n    },\n    order: function (cart) {\n      cart.forEach(function (element) {\n        Carts.update(element._id, {\n          $set: {\n            status: \"ordered\"\n          }\n        });\n      });\n    },\n    recieve_order: function (item_id) {\n      Carts.update(item_id, {\n        $set: {\n          status: \"recieved\"\n        }\n      });\n    },\n    deletes: function (item_id) {\n      Carts.remove(item_id);\n    },\n    save_room: function (event) {\n      if (Rooms.find({\n        roomname: this.save_room_data\n      }).count() == 0) {\n        Rooms.insert({\n          roomname: this.save_room_data\n        });\n      } else {\n        alert(\"duplicate room name\");\n      }\n    },\n    deleteRoom: function (room_id) {\n      Rooms.remove(room_id);\n    }\n  },\n  meteor: {\n    currentUser: function () {\n      return Meteor.user();\n    },\n    currentUsername: function () {\n      if (Meteor.user()) {\n        return Meteor.user().username;\n      } else return \"\";\n    },\n    currentProfile: function () {\n      if (Meteor.user()) {\n        return Meteor.user().profile.permission;\n      } else return \"\";\n    },\n    items: function () {\n      return Items.find({}).fetch();\n    },\n    carts: function () {\n      return Carts.find({\n        userID: Meteor.userId(),\n        status: \"Added To Cart\"\n      }, {\n        sort: {\n          createdAt: -1\n        }\n      }).fetch();\n    },\n    orders: function () {\n      return Carts.find({\n        userID: Meteor.userId(),\n        status: \"ordered\"\n      }, {\n        sort: {\n          createdAt: -1\n        }\n      }).fetch();\n    },\n    recieved: function () {\n      return Carts.find({\n        userID: Meteor.userId(),\n        status: \"recieved\"\n      }, {\n        sort: {\n          createdAt: -1\n        }\n      }).fetch();\n    },\n    incomingOrders: function () {\n      return Carts.find({\n        status: \"ordered\"\n      }, {\n        sort: {\n          createdAt: -1\n        }\n      }).fetch();\n    },\n    approvedOrders: function () {\n      return Carts.find({\n        status: \"recieved\"\n      }, {\n        sort: {\n          createdAt: -1\n        }\n      }).fetch();\n    },\n    rooms: function () {\n      return Rooms.find({}).fetch();\n    },\n    rooms_except: function () {\n      return Rooms.find({\n        roomname: {\n          $nin: [currentUser.profile.roomnumber]\n        }\n      }).fetch();\n    }\n  }\n});","map":{"version":3,"sources":["/Users/gunwoo/OneDrive/College/2020Fall/CSE330S/creativeproject-module7-457175-476801/hotel/imports/ui/App.vue"],"names":["Vue","module","link","v","Meteor","Accounts","Items","Carts","Rooms","exportDefault","components","data","user","username","password","userID","profile","loggedIn","save_Item_Name","save_Item_Description","ordered_items","save_room_data","room_number","methods","register_client","event","call","error","alert","reason","register_manager","login","loginWithPassword","logout","save_Item","insert","name","description","order","console","log","deleteThisItem","item_id","remove","addToCart","id","item","userId","status","createdAt","Date","deleteFromCart","cart","forEach","element","update","_id","$set","recieve_order","deletes","save_room","find","roomname","count","deleteRoom","room_id","meteor","currentUser","currentUsername","currentProfile","permission","items","fetch","carts","sort","orders","recieved","incomingOrders","approvedOrders","rooms","rooms_except","$nin","roomnumber"],"mappings":"AAAA,IAAIA,GAAJ;AAAQC,MAAM,CAACC,IAAP,CAAY,KAAZ,EAAkB;AAAC,aAAQ,UAASC,CAAT,EAAW;AAACH,IAAAA,GAAG,GAACG,CAAJ;AAAM;AAA3B,CAAlB,EAA+C,CAA/C;AAAkD,IAAIC,MAAJ;AAAWH,MAAM,CAACC,IAAP,CAAY,eAAZ,EAA4B;AAACE,EAAAA,MAAM,EAAC,UAASD,CAAT,EAAW;AAACC,IAAAA,MAAM,GAACD,CAAP;AAAS;AAA7B,CAA5B,EAA2D,CAA3D;AAA8D,IAAIE,QAAJ;AAAaJ,MAAM,CAACC,IAAP,CAAY,sBAAZ,EAAmC;AAACG,EAAAA,QAAQ,EAAC,UAASF,CAAT,EAAW;AAACE,IAAAA,QAAQ,GAACF,CAAT;AAAW;AAAjC,CAAnC,EAAsE,CAAtE;AAAyE,IAAIG,KAAJ;AAAUL,MAAM,CAACC,IAAP,CAAY,iBAAZ,EAA8B;AAACI,EAAAA,KAAK,EAAC,UAASH,CAAT,EAAW;AAACG,IAAAA,KAAK,GAACH,CAAN;AAAQ;AAA3B,CAA9B,EAA2D,CAA3D;AAA8D,IAAII,KAAJ;AAAUN,MAAM,CAACC,IAAP,CAAY,iBAAZ,EAA8B;AAACK,EAAAA,KAAK,EAAC,UAASJ,CAAT,EAAW;AAACI,IAAAA,KAAK,GAACJ,CAAN;AAAQ;AAA3B,CAA9B,EAA2D,CAA3D;AAA8D,IAAIK,KAAJ;AAAUP,MAAM,CAACC,IAAP,CAAY,iBAAZ,EAA8B;AAACM,EAAAA,KAAK,EAAC,UAASL,CAAT,EAAW;AAACK,IAAAA,KAAK,GAACL,CAAN;AAAQ;AAA3B,CAA9B,EAA2D,CAA3D;AAAnXF,MAAM,CAACQ,aAAP,CASe;AACbC,EAAAA,UAAU,EAAE,EADC;AAGbC,EAAAA,IAHa,cAGN;AACL,WAAO;AACLC,MAAAA,IAAI,EAAC,EADA;AAELC,MAAAA,QAAQ,EAAC,IAFJ;AAGLC,MAAAA,QAAQ,EAAC,EAHJ;AAILC,MAAAA,MAAM,EAAC,EAJF;AAKLC,MAAAA,OAAO,EAAC,IALH;AAMLC,MAAAA,QAAQ,EAAC,KANJ;AAOLC,MAAAA,cAAc,EAAC,EAPV;AAQLC,MAAAA,qBAAqB,EAAC,EARjB;AASLC,MAAAA,aAAa,EAAC,IATT;AAULC,MAAAA,cAAc,EAAC,IAVV;AAWLC,MAAAA,WAAW,EAAC;AAXP,KAAP;AAaD,GAjBY;AAkBbC,EAAAA,OAAO,EAAE;AACPC,IAAAA,eADO,YACSC,KADT,EACiB;AACpBrB,MAAAA,MAAM,CAACsB,IAAP,CAAY,SAAZ,EAAsB,KAAKd,IAA3B,EAAgC,KAAKE,QAArC,EAA8C,OAA9C,EAAuD,KAAKQ,WAA5D,EAAyE,UAASK,KAAT,EAAe;AACtFC,QAAAA,KAAK,CAACD,KAAK,CAACE,MAAP,CAAL;AACD,OAFD;AAGAjB,MAAAA,IAAI,GAAC,EAAL,EACAE,QAAQ,GAAC,EADT;AAEH,KAPM;AAQPgB,IAAAA,gBARO,YAQUL,KARV,EAQiB;AACpBrB,MAAAA,MAAM,CAACsB,IAAP,CAAY,SAAZ,EAAsB,KAAKd,IAA3B,EAAgC,KAAKE,QAArC,EAA8C,SAA9C,EAAyD,IAAzD,EAA+D,UAASa,KAAT,EAAe;AAC5EC,QAAAA,KAAK,CAACD,KAAK,CAACE,MAAP,CAAL;AACD,OAFD;AAGAjB,MAAAA,IAAI,GAAC,EAAL,EACAE,QAAQ,GAAC,EADT;AAEH,KAdM;AAePiB,IAAAA,KAfO,YAeDN,KAfC,EAeK;AACRrB,MAAAA,MAAM,CAAC4B,iBAAP,CAAyB,KAAKpB,IAA9B,EAAmC,KAAKE,QAAxC,EAAkD,UAASa,KAAT,EAAe;AAC/DC,QAAAA,KAAK,CAACD,KAAK,CAACE,MAAP,CAAL;AACD,OAFD;AAGH,KAnBM;AAoBPI,IAAAA,MApBO,YAoBAR,KApBA,EAoBM;AACTrB,MAAAA,MAAM,CAAC6B,MAAP;AACH,KAtBM;AAuBPC,IAAAA,SAvBO,YAuBGT,KAvBH,EAuBS;AACZnB,MAAAA,KAAK,CAAC6B,MAAN,CAAa;AACXC,QAAAA,IAAI,EAAC,KAAKlB,cADC;AAEXmB,QAAAA,WAAW,EAAC,KAAKlB;AAFN,OAAb;AAIA,WAAKD,cAAL,GAAoB,EAApB,EACA,KAAKC,qBAAL,GAA2B,EAD3B;AAEH,KA9BM;AA+BPmB,IAAAA,KA/BO,YA+BDb,KA/BC,EA+BK;AACVc,MAAAA,OAAO,CAACC,GAAR,CAAY,KAAKpB,aAAjB;AACD,KAjCM;AAkCPqB,IAAAA,cAlCO,YAkCQC,OAlCR,EAkCgB;AACvBpC,MAAAA,KAAK,CAACqC,MAAN,CAAaD,OAAb;AACC,KApCM;AAqCPE,IAAAA,SArCO,YAqCGC,EArCH,EAqCMT,IArCN,EAqCW;AACd7B,MAAAA,KAAK,CAAC4B,MAAN,CAAa;AACTW,QAAAA,IAAI,EAAED,EADG;AAEThC,QAAAA,QAAQ,EAAET,MAAM,CAACQ,IAAP,GAAcC,QAFf;AAGTE,QAAAA,MAAM,EAACX,MAAM,CAAC2C,MAAP,EAHE;AAITC,QAAAA,MAAM,EAAE,eAJC;AAKTZ,QAAAA,IAAI,EAAEA,IALG;AAMTa,QAAAA,SAAS,EAAE,IAAIC,IAAJ;AANF,OAAb;AAQH,KA9CM;AA+CPC,IAAAA,cA/CO,YA+CQT,OA/CR,EA+CgB;AACrBnC,MAAAA,KAAK,CAACoC,MAAN,CAAaD,OAAb;AACD,KAjDM;AAkDPJ,IAAAA,KAlDO,YAkDDc,IAlDC,EAkDI;AACTA,MAAAA,IAAI,CAACC,OAAL,CAAa,UAASC,OAAT,EAAiB;AAC5B/C,QAAAA,KAAK,CAACgD,MAAN,CAAaD,OAAO,CAACE,GAArB,EAAyB;AACvBC,UAAAA,IAAI,EAAG;AAACT,YAAAA,MAAM,EAAE;AAAT;AADgB,SAAzB;AAGD,OAJD;AAKD,KAxDM;AAyDPU,IAAAA,aAzDO,YAyDOhB,OAzDP,EAyDe;AACpBnC,MAAAA,KAAK,CAACgD,MAAN,CAAab,OAAb,EAAqB;AACnBe,QAAAA,IAAI,EAAG;AAACT,UAAAA,MAAM,EAAE;AAAT;AADY,OAArB;AAGD,KA7DM;AA8DPW,IAAAA,OA9DO,YA8DCjB,OA9DD,EA8DS;AACdnC,MAAAA,KAAK,CAACoC,MAAN,CAAaD,OAAb;AACD,KAhEM;AAiEPkB,IAAAA,SAjEO,YAiEGnC,KAjEH,EAiES;AACd,UAAGjB,KAAK,CAACqD,IAAN,CAAW;AAACC,QAAAA,QAAQ,EAAC,KAAKzC;AAAf,OAAX,EAA2C0C,KAA3C,MAAoD,CAAvD,EACA;AACAvD,QAAAA,KAAK,CAAC2B,MAAN,CAAa;AACX2B,UAAAA,QAAQ,EAAC,KAAKzC;AADH,SAAb;AAGC,OALD,MAMI;AAAEO,QAAAA,KAAK,CAAC,qBAAD,CAAL;AAA6B;AACpC,KAzEM;AA0EPoC,IAAAA,UA1EO,YA0EIC,OA1EJ,EA0EY;AACjBzD,MAAAA,KAAK,CAACmC,MAAN,CAAasB,OAAb;AACD;AA5EM,GAlBI;AAiGbC,EAAAA,MAAM,EAAE;AACNC,IAAAA,WADM,cACO;AACX,aAAO/D,MAAM,CAACQ,IAAP,EAAP;AACD,KAHK;AAINwD,IAAAA,eAJM,cAIW;AACf,UAAGhE,MAAM,CAACQ,IAAP,EAAH,EAAiB;AACf,eAAOR,MAAM,CAACQ,IAAP,GAAcC,QAArB;AAA+B,OADjC,MAGE,OAAO,EAAP;AACH,KATK;AAUNwD,IAAAA,cAVM,cAUU;AACd,UAAGjE,MAAM,CAACQ,IAAP,EAAH,EAAiB;AACf,eAAOR,MAAM,CAACQ,IAAP,GAAcI,OAAd,CAAsBsD,UAA7B;AAAyC,OAD3C,MAGE,OAAO,EAAP;AACH,KAfK;AAgBNC,IAAAA,KAhBM,cAgBC;AACL,aAAOjE,KAAK,CAACuD,IAAN,CAAW,EAAX,EAAeW,KAAf,EAAP;AACD,KAlBK;AAmBNC,IAAAA,KAnBM,cAmBC;AACL,aAAOlE,KAAK,CAACsD,IAAN,CAAW;AAAC9C,QAAAA,MAAM,EAACX,MAAM,CAAC2C,MAAP,EAAR;AAAwBC,QAAAA,MAAM,EAAC;AAA/B,OAAX,EAA2D;AAAE0B,QAAAA,IAAI,EAAE;AAAEzB,UAAAA,SAAS,EAAE,CAAC;AAAd;AAAR,OAA3D,EAAwFuB,KAAxF,EAAP;AACD,KArBK;AAsBNG,IAAAA,MAtBM,cAsBE;AACN,aAAOpE,KAAK,CAACsD,IAAN,CAAW;AAAC9C,QAAAA,MAAM,EAACX,MAAM,CAAC2C,MAAP,EAAR;AAAwBC,QAAAA,MAAM,EAAC;AAA/B,OAAX,EAAqD;AAAE0B,QAAAA,IAAI,EAAE;AAAEzB,UAAAA,SAAS,EAAE,CAAC;AAAd;AAAR,OAArD,EAAkFuB,KAAlF,EAAP;AACD,KAxBK;AAyBNI,IAAAA,QAzBM,cAyBI;AACR,aAAOrE,KAAK,CAACsD,IAAN,CAAW;AAAC9C,QAAAA,MAAM,EAACX,MAAM,CAAC2C,MAAP,EAAR;AAAwBC,QAAAA,MAAM,EAAC;AAA/B,OAAX,EAAsD;AAAE0B,QAAAA,IAAI,EAAE;AAAEzB,UAAAA,SAAS,EAAE,CAAC;AAAd;AAAR,OAAtD,EAAmFuB,KAAnF,EAAP;AACD,KA3BK;AA4BNK,IAAAA,cA5BM,cA4BU;AACd,aAAOtE,KAAK,CAACsD,IAAN,CAAW;AAACb,QAAAA,MAAM,EAAC;AAAR,OAAX,EAA8B;AAAE0B,QAAAA,IAAI,EAAE;AAAEzB,UAAAA,SAAS,EAAE,CAAC;AAAd;AAAR,OAA9B,EAA2DuB,KAA3D,EAAP;AACD,KA9BK;AA+BNM,IAAAA,cA/BM,cA+BU;AACd,aAAOvE,KAAK,CAACsD,IAAN,CAAW;AAACb,QAAAA,MAAM,EAAC;AAAR,OAAX,EAA+B;AAAE0B,QAAAA,IAAI,EAAE;AAAEzB,UAAAA,SAAS,EAAE,CAAC;AAAd;AAAR,OAA/B,EAA4DuB,KAA5D,EAAP;AACD,KAjCK;AAkCNO,IAAAA,KAlCM,cAkCC;AACL,aAAOvE,KAAK,CAACqD,IAAN,CAAW,EAAX,EAAeW,KAAf,EAAP;AACD,KApCK;AAqCNQ,IAAAA,YArCM,cAqCQ;AACZ,aAAOxE,KAAK,CAACqD,IAAN,CAAW;AAACC,QAAAA,QAAQ,EAAC;AAACmB,UAAAA,IAAI,EAAC,CAACd,WAAW,CAACnD,OAAZ,CAAoBkE,UAArB;AAAN;AAAV,OAAX,EAA+DV,KAA/D,EAAP;AACD;AAvCK;AAjGK,CATf","sourcesContent":["\nimport Vue from \"vue\";\nimport { Meteor } from \"meteor/meteor\";\nimport { Accounts } from 'meteor/accounts-base';\nimport { Items } from \"../api/items.js\";\nimport { Carts } from \"../api/items.js\";\nimport { Rooms } from \"../api/items.js\";\n// import { Carts } from \"../api/cart.js\"\n\nexport default {\n  components: {\n  },\n  data() {\n    return {\n      user:\"\",\n      username:null,\n      password:\"\",\n      userID:\"\",\n      profile:null,\n      loggedIn:false,\n      save_Item_Name:\"\",\n      save_Item_Description:\"\",\n      ordered_items:null,\n      save_room_data:null,\n      room_number:null\n    };\n  },\n  methods: {\n    register_client(event)  {\n        Meteor.call(\"addUser\",this.user,this.password,\"guest\", this.room_number, function(error){\n          alert(error.reason);\n        });\n        user=\"\",\n        password=\"\"\n    },\n    register_manager(event) {\n        Meteor.call(\"addUser\",this.user,this.password,\"manager\", null, function(error){\n          alert(error.reason);\n        });\n        user=\"\",\n        password=\"\"\n    },\n    login(event){\n        Meteor.loginWithPassword(this.user,this.password, function(error){\n          alert(error.reason);\n        });\n    },\n    logout(event){\n        Meteor.logout();\n    },\n    save_Item(event){\n        Items.insert({\n          name:this.save_Item_Name,\n          description:this.save_Item_Description\n        });\n        this.save_Item_Name=\"\",\n        this.save_Item_Description=\"\"\n    },\n    order(event){\n      console.log(this.ordered_items)\n    },\n    deleteThisItem(item_id){\n    Items.remove(item_id);\n    },\n    addToCart(id,name){\n        Carts.insert({\n            item: id,\n            username: Meteor.user().username,\n            userID:Meteor.userId(),\n            status: \"Added To Cart\",\n            name: name,\n            createdAt: new Date(), \n        });\n    },\n    deleteFromCart(item_id){\n      Carts.remove(item_id);\n    },\n    order(cart){\n      cart.forEach(function(element){\n        Carts.update(element._id,{\n          $set : {status: \"ordered\"}\n        });\n      })\n    },\n    recieve_order(item_id){\n      Carts.update(item_id,{\n        $set : {status: \"recieved\"}\n      });\n    },\n    deletes(item_id){\n      Carts.remove(item_id);\n    },\n    save_room(event){\n      if(Rooms.find({roomname:this.save_room_data}).count()==0)\n      {\n      Rooms.insert({\n        roomname:this.save_room_data\n      });\n      }\n      else{ alert(\"duplicate room name\")}\n    },\n    deleteRoom(room_id){\n      Rooms.remove(room_id)\n    }\n  },\n\n  meteor: {\n    currentUser(){\n      return Meteor.user();\n    },\n    currentUsername(){\n      if(Meteor.user()){\n        return Meteor.user().username;}\n      else \n        return \"\";\n    },\n    currentProfile(){\n      if(Meteor.user()){\n        return Meteor.user().profile.permission;}\n      else\n        return \"\";\n    },\n    items(){\n      return Items.find({}).fetch();\n    },\n    carts(){\n      return Carts.find({userID:Meteor.userId(),status:\"Added To Cart\"},{ sort: { createdAt: -1 } }).fetch();\n    },\n    orders(){\n      return Carts.find({userID:Meteor.userId(),status:\"ordered\"},{ sort: { createdAt: -1 } }).fetch();\n    },\n    recieved(){\n      return Carts.find({userID:Meteor.userId(),status:\"recieved\"},{ sort: { createdAt: -1 } }).fetch();\n    },\n    incomingOrders(){\n      return Carts.find({status:\"ordered\"},{ sort: { createdAt: -1 } }).fetch();\n    },\n    approvedOrders(){\n      return Carts.find({status:\"recieved\"},{ sort: { createdAt: -1 } }).fetch();\n    },\n    rooms(){\n      return Rooms.find({}).fetch();\n    },\n    rooms_except(){\n      return Rooms.find({roomname:{$nin:[currentUser.profile.roomnumber]}}).fetch();\n    }\n  }\n};\n"]},"sourceType":"module","hash":"fe05fe254398df855ca7ec9adf01c4bbfd7ed3c9"}
